config/settings.py
config/urls.py
huscy/bookings/__init__.py
huscy/bookings/api_urls.py
huscy/bookings/apps.py
huscy/bookings/models.py
huscy/bookings/serializers.py
huscy/bookings/services.py
huscy/bookings/views.py
huscy/bookings/migrations/0001_initial.py
huscy/bookings/migrations/__init__.py
tests/conftest.py
tests/test_book_timeslot.py
tests/test_create_timeslot.py
tests/test_delete_timeslot.py
tests/test_timeslot.py
tests/test_timeslot_manager.py
tests/test_unbook_timeslot.py
tests/test_update_timeslot.py
tests/serializer/test_timeslot_serializer.py
tests/services/test_get_timeslots.py
tests/viewsets/test_list_timeslots_viewset.py
huscy.bookings-0.4.1a12.dist-info/LICENSE
huscy.bookings-0.4.1a12.dist-info/METADATA
huscy.bookings-0.4.1a12.dist-info/WHEEL
huscy.bookings-0.4.1a12.dist-info/top_level.txt
huscy.bookings-0.4.1a12.dist-info/RECORD
